vector-mac-accelerator/rtl/mac_accelerator.v
// =============================================================
// mac_accelerator.v
// Parameterized Vector MAC (Multiply-Accumulate) Accelerator
// Y = SUM(A[i] * B[i]), i = 0 .. VECTOR_LEN-1
// Streaming-operand interface, single MAC unit, sequential FSM
// =============================================================

module mac_accelerator #(
    parameter DATA_WIDTH = 8,
    parameter ACC_WIDTH  = 32,
    parameter VECTOR_LEN = 8
) (
    input                       clk,
    input                       rst_n,     // active-low async reset
    input                       start,     // pulse to begin a sequence
    input      [DATA_WIDTH-1:0] a_in,
    input      [DATA_WIDTH-1:0] b_in,
    output reg [ACC_WIDTH-1:0]  result,
    output                      busy,
    output reg                  done
);

    // ---------------------------------------------------------
    // FSM state encoding
    // ---------------------------------------------------------
    localparam S_IDLE    = 2'b00;
    localparam S_COMPUTE = 2'b01;
    localparam S_DONE    = 2'b10;

    reg [1:0] state, state_next;

    // ---------------------------------------------------------
    // Index counter width, derived from VECTOR_LEN (no magic numbers)
    // ---------------------------------------------------------
    localparam CNT_WIDTH = (VECTOR_LEN <= 1) ? 1 : $clog2(VECTOR_LEN);

    reg [CNT_WIDTH-1:0] count;
    reg [ACC_WIDTH-1:0] acc_reg;

    // ---------------------------------------------------------
    // Combinational datapath: multiplier
    // ---------------------------------------------------------
    wire [2*DATA_WIDTH-1:0] product;
    assign product = a_in * b_in;

    // ---------------------------------------------------------
    // Sequential: FSM state register
    // ---------------------------------------------------------
    always @(posedge clk or negedge rst_n) begin
        if (!rst_n)
            state <= S_IDLE;
        else
            state <= state_next;
    end

    // ---------------------------------------------------------
    // Combinational: next-state logic
    // ---------------------------------------------------------
    always @(*) begin
        state_next = state;
        case (state)
            S_IDLE: begin
                if (start)
                    // VECTOR_LEN==1: the single MAC happens right here in this
                    // transition cycle, so go straight to DONE next cycle.
                    state_next = (VECTOR_LEN == 1) ? S_DONE : S_COMPUTE;
            end
            S_COMPUTE: begin
                // count == number of elements already accumulated *before*
                // this cycle. If VECTOR_LEN-1 of them are already done, this
                // cycle's accumulate is the final (Nth) one.
                if (count == VECTOR_LEN-1)
                    state_next = S_DONE;
            end
            S_DONE: begin
                state_next = S_IDLE;
            end
            default: state_next = S_IDLE;
        endcase
    end

    // ---------------------------------------------------------
    // Sequential: counter, accumulator, result, done
    // ---------------------------------------------------------
    always @(posedge clk or negedge rst_n) begin
        if (!rst_n) begin
            count   <= {CNT_WIDTH{1'b0}};
            acc_reg <= {ACC_WIDTH{1'b0}};
            result  <= {ACC_WIDTH{1'b0}};
            done    <= 1'b0;
        end else begin
            done <= 1'b0; // default: single-cycle pulse

            case (state)
                S_IDLE: begin
                    if (start) begin
                        // a_in/b_in already hold element 0 this cycle -
                        // accumulate it now instead of wasting the cycle.
                        acc_reg <= product;
                        count   <= {CNT_WIDTH{1'b0}} + 1'b1;
                    end
                end

                S_COMPUTE: begin
                    acc_reg <= acc_reg + product;
                    if (count != VECTOR_LEN-1)
                        count <= count + 1'b1;
                end

                S_DONE: begin
                    result <= acc_reg;
                    done   <= 1'b1;
                end

                default: ; // no-op
            endcase
        end
    end

    // ---------------------------------------------------------
    // Output: busy
    // ---------------------------------------------------------
    assign busy = (state == S_COMPUTE);

endmodule

vector-mac-accelerator/tb/mac_accelerator_tb.v
// =============================================================
// mac_accelerator_tb.v
// Self-checking testbench for mac_accelerator
// Two DUT instances: default (VECTOR_LEN=8) and VECTOR_LEN=4
// to exercise different configurations.
// =============================================================
`timescale 1ns/1ps

module mac_accelerator_tb;

    localparam DATA_WIDTH = 8;
    localparam ACC_WIDTH  = 32;

    // -------- DUT #1: default VECTOR_LEN = 8 --------
    localparam VLEN8 = 8;
    reg                     clk;
    reg                     rst_n;
    reg                     start8;
    reg  [DATA_WIDTH-1:0]   a_in8, b_in8;
    wire [ACC_WIDTH-1:0]    result8;
    wire                    busy8, done8;

    mac_accelerator #(.DATA_WIDTH(DATA_WIDTH), .ACC_WIDTH(ACC_WIDTH), .VECTOR_LEN(VLEN8)) dut8 (
        .clk(clk), .rst_n(rst_n), .start(start8),
        .a_in(a_in8), .b_in(b_in8),
        .result(result8), .busy(busy8), .done(done8)
    );

    // -------- DUT #2: VECTOR_LEN = 4 (different config) --------
    localparam VLEN4 = 4;
    reg                     start4;
    reg  [DATA_WIDTH-1:0]   a_in4, b_in4;
    wire [ACC_WIDTH-1:0]    result4;
    wire                    busy4, done4;

    mac_accelerator #(.DATA_WIDTH(DATA_WIDTH), .ACC_WIDTH(ACC_WIDTH), .VECTOR_LEN(VLEN4)) dut4 (
        .clk(clk), .rst_n(rst_n), .start(start4),
        .a_in(a_in4), .b_in(b_in4),
        .result(result4), .busy(busy4), .done(done4)
    );

    // -------- Clock: 10ns period --------
    initial clk = 0;
    always #5 clk = ~clk;

    integer pass_count = 0;
    integer fail_count = 0;

    // -------------------------------------------------------
    // Reusable task: run one MAC sequence on DUT8, check result
    // a_arr/b_arr are pre-loaded into memory arrays by the caller
    // -------------------------------------------------------
    reg [DATA_WIDTH-1:0] a_mem [0:31];
    reg [DATA_WIDTH-1:0] b_mem [0:31];

    task run_vec8;
        input [8*32-1:0] test_name; // for display only, packed string
        input integer len;
        integer i;
        reg [ACC_WIDTH-1:0] expected;
        begin
            expected = 0;
            for (i = 0; i < len; i = i + 1)
                expected = expected + (a_mem[i] * b_mem[i]);

            @(negedge clk);
            start8 = 1;
            a_in8 = a_mem[0];
            b_in8 = b_mem[0];
            @(negedge clk);
            start8 = 0;
            // from here, busy8 should be high; drive remaining elements
            for (i = 1; i < len; i = i + 1) begin
                a_in8 = a_mem[i];
                b_in8 = b_mem[i];
                @(negedge clk);
            end

            // wait for done
            wait (done8 == 1);
            #1;
            if (result8 === expected) begin
                $display("PASS [%0s] result=%0d expected=%0d", test_name, result8, expected);
                pass_count = pass_count + 1;
            end else begin
                $display("FAIL [%0s] result=%0d expected=%0d", test_name, result8, expected);
                fail_count = fail_count + 1;
            end
            @(negedge clk); // let DONE pulse retire, FSM back to IDLE
        end
    endtask

    integer j;

    initial begin
        $dumpfile("waveform.vcd");
        $dumpvars(0, mac_accelerator_tb);

        // ---------------- init ----------------
        rst_n  = 0;
        start8 = 0; a_in8 = 0; b_in8 = 0;
        start4 = 0; a_in4 = 0; b_in4 = 0;

        repeat (3) @(negedge clk);

        // ================= TEST 1: Reset behavior =================
        if (result8 === 0 && busy8 === 0 && done8 === 0)
            begin $display("PASS [Reset] outputs are 0 after reset"); pass_count = pass_count+1; end
        else
            begin $display("FAIL [Reset] result=%0d busy=%0b done=%0b", result8, busy8, done8); fail_count = fail_count+1; end

        rst_n = 1;
        @(negedge clk);

        // ================= TEST 2: Single MAC-sequence, small positive values =================
        for (j = 0; j < 8; j = j + 1) begin a_mem[j] = j+1; b_mem[j] = j+2; end
        run_vec8("Positive values", 8);

        // ================= TEST 3: All-zero inputs =================
        for (j = 0; j < 8; j = j + 1) begin a_mem[j] = 0; b_mem[j] = 0; end
        run_vec8("All-zero inputs", 8);

        // ================= TEST 4: Maximum input values (255*255*8) =================
        for (j = 0; j < 8; j = j + 1) begin a_mem[j] = 255; b_mem[j] = 255; end
        run_vec8("Max input values", 8);

        // ================= TEST 5: Multiple consecutive operations (back to back) =================
        for (j = 0; j < 8; j = j + 1) begin a_mem[j] = 2; b_mem[j] = 3; end
        run_vec8("Consecutive op #1", 8);
        for (j = 0; j < 8; j = j + 1) begin a_mem[j] = 5; b_mem[j] = 1; end
        run_vec8("Consecutive op #2", 8);
        for (j = 0; j < 8; j = j + 1) begin a_mem[j] = 10; b_mem[j] = 10; end
        run_vec8("Consecutive op #3", 8);

        // ================= TEST 6: start asserted while busy (must be ignored) =================
        for (j = 0; j < 8; j = j + 1) begin a_mem[j] = 1; b_mem[j] = 1; end
        begin : start_while_busy_test
            reg [ACC_WIDTH-1:0] expected;
            expected = 8; // sum of 1*1 eight times
            @(negedge clk);
            start8 = 1; a_in8 = a_mem[0]; b_in8 = b_mem[0];
            @(negedge clk);
            start8 = 1; // illegally re-assert start mid-sequence
            a_in8 = a_mem[1]; b_in8 = b_mem[1];
            @(negedge clk);
            start8 = 0;
            for (j = 2; j < 8; j = j + 1) begin
                a_in8 = a_mem[j]; b_in8 = b_mem[j];
                @(negedge clk);
            end
            wait (done8 == 1);
            #1;
            if (result8 === expected) begin
                $display("PASS [start-while-busy ignored] result=%0d expected=%0d", result8, expected);
                pass_count = pass_count + 1;
            end else begin
                $display("FAIL [start-while-busy ignored] result=%0d expected=%0d", result8, expected);
                fail_count = fail_count + 1;
            end
            @(negedge clk);
        end

        // ================= TEST 7: Different vector length (VECTOR_LEN=4 instance) =================
        begin : vlen4_test
            reg [ACC_WIDTH-1:0] expected;
            reg [DATA_WIDTH-1:0] a4 [0:3];
            reg [DATA_WIDTH-1:0] b4 [0:3];
            integer k;
            a4[0]=3; a4[1]=4; a4[2]=5; a4[3]=6;
            b4[0]=1; b4[1]=2; b4[2]=3; b4[3]=4;
            expected = 3*1 + 4*2 + 5*3 + 6*4; // 3+8+15+24 = 50

            @(negedge clk);
            start4 = 1; a_in4 = a4[0]; b_in4 = b4[0];
            @(negedge clk);
            start4 = 0;
            for (k = 1; k < 4; k = k + 1) begin
                a_in4 = a4[k]; b_in4 = b4[k];
                @(negedge clk);
            end
            wait (done4 == 1);
            #1;
            if (result4 === expected) begin
                $display("PASS [VECTOR_LEN=4] result=%0d expected=%0d", result4, expected);
                pass_count = pass_count + 1;
            end else begin
                $display("FAIL [VECTOR_LEN=4] result=%0d expected=%0d", result4, expected);
                fail_count = fail_count + 1;
            end
            @(negedge clk);
        end

        // ================= TEST 8: Reset asserted mid-computation =================
        begin : reset_mid_test
            for (j = 0; j < 8; j = j + 1) begin a_mem[j] = 9; b_mem[j] = 9; end
            @(negedge clk);
            start8 = 1; a_in8 = a_mem[0]; b_in8 = b_mem[0];
            @(negedge clk);
            start8 = 0; a_in8 = a_mem[1]; b_in8 = b_mem[1];
            @(negedge clk); // now mid-COMPUTE
            rst_n = 0; // assert reset mid-sequence
            @(negedge clk);
            rst_n = 1;
            if (busy8 === 0 && done8 === 0) begin
                $display("PASS [Reset mid-computation] FSM returned to IDLE, busy=0 done=0");
                pass_count = pass_count + 1;
            end else begin
                $display("FAIL [Reset mid-computation] busy=%0b done=%0b", busy8, done8);
                fail_count = fail_count + 1;
            end
            @(negedge clk);
        end

        // ================= TEST 9: Post-reset-mid-op, verify DUT still works correctly =================
        for (j = 0; j < 8; j = j + 1) begin a_mem[j] = 4; b_mem[j] = 4; end
        run_vec8("Functional after mid-op reset", 8);

        // ================= TEST 10: Done is exactly one cycle =================
        begin : done_pulse_test
            integer done_cycles;
            done_cycles = 0;
            for (j = 0; j < 8; j = j + 1) begin a_mem[j] = 1; b_mem[j] = 2; end
            @(negedge clk);
            start8 = 1; a_in8 = a_mem[0]; b_in8 = b_mem[0];
            @(negedge clk);
            start8 = 0;
            for (j = 1; j < 8; j = j + 1) begin
                a_in8 = a_mem[j]; b_in8 = b_mem[j];
                @(negedge clk);
            end
            // now DUT should be transitioning to DONE; sample done over next 3 cycles
            repeat (3) begin
                @(negedge clk);
                if (done8) done_cycles = done_cycles + 1;
            end
            if (done_cycles == 1) begin
                $display("PASS [Done single-cycle pulse] done asserted for exactly 1 cycle");
                pass_count = pass_count + 1;
            end else begin
                $display("FAIL [Done single-cycle pulse] done asserted for %0d cycles", done_cycles);
                fail_count = fail_count + 1;
            end
        end

        // ================= Summary =================
        $display("----------------------------------------------------");
        $display("TOTAL: %0d PASS, %0d FAIL", pass_count, fail_count);
        if (fail_count == 0)
            $display("=== ALL TESTS PASSED ===");
        else
            $display("=== TESTS FAILED ===");
        $display("----------------------------------------------------");

        $finish;
    end

endmodule

vector-mac-accelerator/simulation/waveform.vcd
$date
	Wed Aug 12 07:14:01 2026
$end
$version
	Icarus Verilog
$end
$timescale
	1ps
$end
$scope module mac_accelerator_tb $end
$var wire 32 ! result8 [31:0] $end
$var wire 32 " result4 [31:0] $end
$var wire 1 # done8 $end
$var wire 1 $ done4 $end
$var wire 1 % busy8 $end
$var wire 1 & busy4 $end
$var parameter 32 ' ACC_WIDTH $end
$var parameter 32 ( DATA_WIDTH $end
$var parameter 32 ) VLEN4 $end
$var parameter 32 * VLEN8 $end
$var reg 8 + a_in4 [7:0] $end
$var reg 8 , a_in8 [7:0] $end
$var reg 8 - b_in4 [7:0] $end
$var reg 8 . b_in8 [7:0] $end
$var reg 1 / clk $end
$var reg 1 0 rst_n $end
$var reg 1 1 start4 $end
$var reg 1 2 start8 $end
$var integer 32 3 fail_count [31:0] $end
$var integer 32 4 j [31:0] $end
$var integer 32 5 pass_count [31:0] $end
$scope module dut4 $end
$var wire 8 6 a_in [7:0] $end
$var wire 8 7 b_in [7:0] $end
$var wire 1 / clk $end
$var wire 1 0 rst_n $end
$var wire 1 1 start $end
$var wire 16 8 product [15:0] $end
$var wire 1 & busy $end
$var parameter 32 9 ACC_WIDTH $end
$var parameter 32 : CNT_WIDTH $end
$var parameter 32 ; DATA_WIDTH $end
$var parameter 2 < S_COMPUTE $end
$var parameter 2 = S_DONE $end
$var parameter 2 > S_IDLE $end
$var parameter 32 ? VECTOR_LEN $end
$var reg 32 @ acc_reg [31:0] $end
$var reg 2 A count [1:0] $end
$var reg 1 $ done $end
$var reg 32 B result [31:0] $end
$var reg 2 C state [1:0] $end
$var reg 2 D state_next [1:0] $end
$upscope $end
$scope module dut8 $end
$var wire 8 E a_in [7:0] $end
$var wire 8 F b_in [7:0] $end
$var wire 1 / clk $end
$var wire 1 0 rst_n $end
$var wire 1 2 start $end
$var wire 16 G product [15:0] $end
$var wire 1 % busy $end
$var parameter 32 H ACC_WIDTH $end
$var parameter 32 I CNT_WIDTH $end
$var parameter 32 J DATA_WIDTH $end
$var parameter 2 K S_COMPUTE $end
$var parameter 2 L S_DONE $end
$var parameter 2 M S_IDLE $end
$var parameter 32 N VECTOR_LEN $end
$var reg 32 O acc_reg [31:0] $end
$var reg 3 P count [2:0] $end
$var reg 1 # done $end
$var reg 32 Q result [31:0] $end
$var reg 2 R state [1:0] $end
$var reg 2 S state_next [1:0] $end
$upscope $end
$scope begin done_pulse_test $end
$var integer 32 T done_cycles [31:0] $end
$upscope $end
$scope begin reset_mid_test $end
$upscope $end
$scope begin start_while_busy_test $end
$var reg 32 U expected [31:0] $end
$upscope $end
$scope begin vlen4_test $end
$var reg 32 V expected [31:0] $end
$var integer 32 W k [31:0] $end
$upscope $end
$scope task run_vec8 $end
$var reg 32 X expected [31:0] $end
$var reg 256 Y test_name [255:0] $end
$var integer 32 Z i [31:0] $end
$var integer 32 [ len [31:0] $end
$upscope $end
$upscope $end
$enddefinitions $end
$comment Show the parameter values. $end
$dumpall
b1000 N
b0 M
b10 L
b1 K
b1000 J
b11 I
b100000 H
b100 ?
b0 >
b10 =
b1 <
b1000 ;
b10 :
b100000 9
b1000 *
b100 )
b1000 (
b100000 '
$end
#0
$dumpvars
bx [
bx Z
bx Y
bx X
bx W
bx V
bx U
bx T
b0 S
b0 R
b0 Q
b0 P
b0 O
b0 G
b0 F
b0 E
b0 D
b0 C
b0 B
b0 A
b0 @
b0 8
b0 7
b0 6
b0 5
bx 4
b0 3
02
01
00
0/
b0 .
b0 -
b0 ,
b0 +
0&
0%
0$
0#
b0 "
b0 !
$end
#5000
1/
#10000
0/
#15000
1/
#20000
0/
#25000
1/
#30000
10
b1 5
0/
#35000
1/
#40000
b1000 Z
b11110000 X
b1000 [
b10100000110111101110011011010010111010001101001011101100110010100100000011101100110000101101100011101010110010101110011 Y
b1000 4
0/
#45000
1/
#50000
b1 S
b10 G
b10 .
b10 F
b1 ,
b1 E
12
0/
#55000
1%
b1 R
b1 P
b10 O
1/
#60000
b11 .
b11 F
b110 G
b10 ,
b10 E
b1 Z
02
0/
#65000
b10 P
b1000 O
1/
#70000
b100 .
b100 F
b1100 G
b11 ,
b11 E
b10 Z
0/
#75000
b11 P
b10100 O
1/
#80000
b101 .
b101 F
b10100 G
b100 ,
b100 E
b11 Z
0/
#85000
b100 P
b101000 O
1/
#90000
b110 .
b110 F
b11110 G
b101 ,
b101 E
b100 Z
0/
#95000
b101 P
b1000110 O
1/
#100000
b111 .
b111 F
b101010 G
b110 ,
b110 E
b101 Z
0/
#105000
b110 P
b1110000 O
1/
#110000
b1000 .
b1000 F
b111000 G
b111 ,
b111 E
b110 Z
0/
#115000
b10 S
b111 P
b10101000 O
1/
#120000
b1001 .
b1001 F
b1001000 G
b1000 ,
b1000 E
b111 Z
0/
#125000
b0 S
b11110000 O
0%
b10 R
1/
#130000
b1000 Z
0/
#135000
b0 R
1#
b11110000 !
b11110000 Q
1/
#136000
b10 5
#140000
b1000 Z
b0 X
b10000010110110001101100001011010111101001100101011100100110111100100000011010010110111001110000011101010111010001110011 Y
b1000 4
0/
#145000
0#
1/
#150000
b1 S
b0 .
b0 F
b0 G
b0 ,
b0 E
12
0/
#155000
1%
b1 R
b1 P
b0 O
1/
#160000
b1 Z
02
0/
#165000
b10 P
1/
#170000
b10 Z
0/
#175000
b11 P
1/
#180000
b11 Z
0/
#185000
b100 P
1/
#190000
b100 Z
0/
#195000
b101 P
1/
#200000
b101 Z
0/
#205000
b110 P
1/
#210000
b110 Z
0/
#215000
b10 S
b111 P
1/
#220000
b111 Z
0/
#225000
b0 S
0%
b10 R
1/
#230000
b1000 Z
0/
#235000
b0 R
1#
b0 !
b0 Q
1/
#236000
b11 5
#240000
b1111111000000001000 X
b1000 Z
b1001101011000010111100000100000011010010110111001110000011101010111010000100000011101100110000101101100011101010110010101110011 Y
b1000 4
0/
#245000
0#
1/
#250000
b1 S
b1111111000000001 G
b11111111 .
b11111111 F
b11111111 ,
b11111111 E
12
0/
#255000
1%
b1 R
b1 P
b1111111000000001 O
1/
#260000
b1 Z
02
0/
#265000
b10 P
b11111110000000010 O
1/
#270000
b10 Z
0/
#275000
b11 P
b101111101000000011 O
1/
#280000
b11 Z
0/
#285000
b100 P
b111111100000000100 O
1/
#290000
b100 Z
0/
#295000
b101 P
b1001111011000000101 O
1/
#300000
b101 Z
0/
#305000
b110 P
b1011111010000000110 O
1/
#310000
b110 Z
0/
#315000
b10 S
b111 P
b1101111001000000111 O
1/
#320000
b111 Z
0/
#325000
b0 S
b1111111000000001000 O
0%
b10 R
1/
#330000
b1000 Z
0/
#335000
b0 R
1#
b1111111000000001000 !
b1111111000000001000 Q
1/
#336000
b100 5
#340000
b1000 Z
b110000 X
b100001101101111011011100111001101100101011000110111010101110100011010010111011001100101001000000110111101110000001000000010001100110001 Y
b1000 4
0/
#345000
0#
1/
#350000
b1 S
b11 .
b11 F
b110 G
b10 ,
b10 E
12
0/
#355000
1%
b1 R
b1 P
b110 O
1/
#360000
b1 Z
02
0/
#365000
b10 P
b1100 O
1/
#370000
b10 Z
0/
#375000
b11 P
b10010 O
1/
#380000
b11 Z
0/
#385000
b100 P
b11000 O
1/
#390000
b100 Z
0/
#395000
b101 P
b11110 O
1/
#400000
b101 Z
0/
#405000
b110 P
b100100 O
1/
#410000
b110 Z
0/
#415000
b10 S
b111 P
b101010 O
1/
#420000
b111 Z
0/
#425000
b0 S
b110000 O
0%
b10 R
1/
#430000
b1000 Z
0/
#435000
b0 R
1#
b110000 !
b110000 Q
1/
#436000
b101 5
#440000
b1000 Z
b101000 X
b100001101101111011011100111001101100101011000110111010101110100011010010111011001100101001000000110111101110000001000000010001100110010 Y
b1000 4
0/
#445000
0#
1/
#450000
b1 S
b1 .
b1 F
b101 G
b101 ,
b101 E
12
0/
#455000
1%
b1 R
b1 P
b101 O
1/
#460000
b1 Z
02
0/
#465000
b10 P
b1010 O
1/
#470000
b10 Z
0/
#475000
b11 P
b1111 O
1/
#480000
b11 Z
0/
#485000
b100 P
b10100 O
1/
#490000
b100 Z
0/
#495000
b101 P
b11001 O
1/
#500000
b101 Z
0/
#505000
b110 P
b11110 O
1/
#510000
b110 Z
0/
#515000
b10 S
b111 P
b100011 O
1/
#520000
b111 Z
0/
#525000
b0 S
b101000 O
0%
b10 R
1/
#530000
b1000 Z
0/
#535000
b0 R
1#
b101000 !
b101000 Q
1/
#536000
b110 5
#540000
b1000 Z
b1100100000 X
b100001101101111011011100111001101100101011000110111010101110100011010010111011001100101001000000110111101110000001000000010001100110011 Y
b1000 4
0/
#545000
0#
1/
#550000
b1 S
b1010 .
b1010 F
b1100100 G
b1010 ,
b1010 E
12
0/
#555000
1%
b1 R
b1 P
b1100100 O
1/
#560000
b1 Z
02
0/
#565000
b10 P
b11001000 O
1/
#570000
b10 Z
0/
#575000
b11 P
b100101100 O
1/
#580000
b11 Z
0/
#585000
b100 P
b110010000 O
1/
#590000
b100 Z
0/
#595000
b101 P
b111110100 O
1/
#600000
b101 Z
0/
#605000
b110 P
b1001011000 O
1/
#610000
b110 Z
0/
#615000
b10 S
b111 P
b1010111100 O
1/
#620000
b111 Z
0/
#625000
b0 S
b1100100000 O
0%
b10 R
1/
#630000
b1000 Z
0/
#635000
b0 R
1#
b1100100000 !
b1100100000 Q
1/
#636000
b111 5
#640000
b1000 U
b1000 4
0/
#645000
0#
1/
#650000
b1 S
b1 .
b1 F
b1 G
b1 ,
b1 E
12
0/
#655000
1%
b1 R
b1 P
b1 O
1/
#660000
0/
#665000
b10 P
b10 O
1/
#670000
b10 4
02
0/
#675000
b11 P
b11 O
1/
#680000
b11 4
0/
#685000
b100 P
b100 O
1/
#690000
b100 4
0/
#695000
b101 P
b101 O
1/
#700000
b101 4
0/
#705000
b110 P
b110 O
1/
#710000
b110 4
0/
#715000
b10 S
b111 P
b111 O
1/
#720000
b111 4
0/
#725000
b0 S
b1000 O
0%
b10 R
1/
#730000
b1000 4
0/
#735000
b0 R
1#
b1000 !
b1000 Q
1/
#736000
b1000 5
#740000
b110010 V
0/
#745000
0#
1/
#750000
b1 D
b11 8
b1 -
b1 7
b11 +
b11 6
11
0/
#755000
1&
b1 C
b1 A
b11 @
1/
#760000
b10 -
b10 7
b1000 8
b100 +
b100 6
b1 W
01
0/
#765000
b10 A
b1011 @
1/
#770000
b11 -
b11 7
b1111 8
b101 +
b101 6
b10 W
0/
#775000
b10 D
b11 A
b11010 @
1/
#780000
b100 -
b100 7
b11000 8
b110 +
b110 6
b11 W
0/
#785000
b0 D
b110010 @
0&
b10 C
1/
#790000
b100 W
0/
#795000
b0 C
1$
b110010 "
b110010 B
1/
#796000
b1001 5
#800000
b1000 4
0/
#805000
0$
1/
#810000
b1 S
b1001 .
b1001 F
b1010001 G
b1001 ,
b1001 E
12
0/
#815000
1%
b1 R
b1 P
b1010001 O
1/
#820000
02
0/
#825000
b10 P
b10100010 O
1/
#830000
b0 S
0%
b0 R
b0 !
b0 Q
b0 O
b0 P
b0 "
b0 B
b0 @
b0 A
00
0/
#835000
1/
#840000
b1010 5
10
0/
#845000
1/
#850000
b1000 Z
b10000000 X
b100011001110101011011100110001101110100011010010110111101101110011000010110110000100000011000010110011001110100011001010111001000100000011011010110100101100100001011010110111101110000001000000111001001100101011100110110010101110100 Y
b1000 4
0/
#855000
1/
#860000
b1 S
b100 .
b100 F
b10000 G
b100 ,
b100 E
12
0/
#865000
1%
b1 R
b1 P
b10000 O
1/
#870000
b1 Z
02
0/
#875000
b10 P
b100000 O
1/
#880000
b10 Z
0/
#885000
b11 P
b110000 O
1/
#890000
b11 Z
0/
#895000
b100 P
b1000000 O
1/
#900000
b100 Z
0/
#905000
b101 P
b1010000 O
1/
#910000
b101 Z
0/
#915000
b110 P
b1100000 O
1/
#920000
b110 Z
0/
#925000
b10 S
b111 P
b1110000 O
1/
#930000
b111 Z
0/
#935000
b0 S
b10000000 O
0%
b10 R
1/
#940000
b1000 Z
0/
#945000
b0 R
1#
b10000000 !
b10000000 Q
1/
#946000
b1011 5
#950000
b1000 4
b0 T
0/
#955000
0#
1/
#960000
b1 S
b10 .
b10 F
b10 G
b1 ,
b1 E
12
0/
#965000
1%
b1 R
b1 P
b10 O
1/
#970000
b1 4
02
0/
#975000
b10 P
b100 O
1/
#980000
b10 4
0/
#985000
b11 P
b110 O
1/
#990000
b11 4
0/
#995000
b100 P
b1000 O
1/
#1000000
b100 4
0/
#1005000
b101 P
b1010 O
1/
#1010000
b101 4
0/
#1015000
b110 P
b1100 O
1/
#1020000
b110 4
0/
#1025000
b10 S
b111 P
b1110 O
1/
#1030000
b111 4
0/
#1035000
b0 S
b10000 O
0%
b10 R
1/
#1040000
b1000 4
0/
#1045000
b0 R
1#
b10000 !
b10000 Q
1/
#1050000
b1 T
0/
#1055000
0#
1/
#1060000
0/
#1065000
1/
#1070000
b1100 5
0/
